rawsteel_music_player-1.0.6.dist-info/METADATA
rawsteel_music_player-1.0.6.dist-info/RECORD
rawsteel_music_player-1.0.6.dist-info/WHEEL
rawsteel_music_player-1.0.6.dist-info/entry_points.txt
rawsteel_music_player-1.0.6.dist-info/top_level.txt
rawsteelp/__init__.py
rawsteelp/rawsteelp.py
