Metadata-Version: 2.1
Name: rawsteel-music-player
Version: 1.0.6
Summary: A minimal music player with lyric show
Home-page: https://github.com/baijifeilong/rawsteelp
Author: BaiJiFeiLong
Author-email: baijifeilong@gmail.com
License: GPL3
Platform: UNKNOWN
